.gitignore
MANIFEST.in
README.rst
bootstrap-buildout.py
buildout.cfg
setup.cfg
setup.py
docs/HISTORY.txt
raptus/__init__.py
raptus.autocompletewidget.egg-info/PKG-INFO
raptus.autocompletewidget.egg-info/SOURCES.txt
raptus.autocompletewidget.egg-info/dependency_links.txt
raptus.autocompletewidget.egg-info/entry_points.txt
raptus.autocompletewidget.egg-info/namespace_packages.txt
raptus.autocompletewidget.egg-info/not-zip-safe
raptus.autocompletewidget.egg-info/requires.txt
raptus.autocompletewidget.egg-info/top_level.txt
raptus/autocompletewidget/__init__.py
raptus/autocompletewidget/configure.zcml
raptus/autocompletewidget/interfaces.py
raptus/autocompletewidget/testing.py
raptus/autocompletewidget/widget.py
raptus/autocompletewidget/Extensions/Install.py
raptus/autocompletewidget/Extensions/__init__.py
raptus/autocompletewidget/profiles/default/cssregistry.xml
raptus/autocompletewidget/profiles/default/jsregistry.xml
raptus/autocompletewidget/profiles/default/metadata.xml
raptus/autocompletewidget/profiles/default/skins.xml
raptus/autocompletewidget/profiles/uninstall/cssregistry.xml
raptus/autocompletewidget/profiles/uninstall/jsregistry.xml
raptus/autocompletewidget/skins/autocompletewidget/autocomplete.pt
raptus/autocompletewidget/skins/autocompletewidget/autocompletemulti.pt
raptus/autocompletewidget/skins/autocompletewidget/indicator.gif
raptus/autocompletewidget/skins/autocompletewidget/jquery.autocomplete.css.dtml
raptus/autocompletewidget/skins/autocompletewidget/jquery.autocomplete.js
raptus/autocompletewidget/skins/autocompletewidget/jquery.autocomplete.min.js
raptus/autocompletewidget/skins/autocompletewidget/jquery.bgiframe.min.js
raptus/autocompletewidget/tests/__init__.py
raptus/autocompletewidget/tests/test_widget.py