Metadata-Version: 1.1
Name: raptus.autocompletewidget
Version: 1.0b4
Summary: archetypes autocomplete widget
Home-page: https://github.com/Raptus/raptus.autocompletewidget
Author: Raptus AG
Author-email: dev@raptus.com
License: GPL
Keywords: plone archetypes widget autocomplete
Platform: UNKNOWN
Classifier: Programming Language :: Python
Classifier: Topic :: Software Development :: Libraries :: Python Modules
